setup.cfg
setup.py
adp_connection/__init__.py
adp_connection/version.py
adp_connection.egg-info/PKG-INFO
adp_connection.egg-info/SOURCES.txt
adp_connection.egg-info/dependency_links.txt
adp_connection.egg-info/entry_points.txt
adp_connection.egg-info/requires.txt
adp_connection.egg-info/top_level.txt
adp_connection/lib/__init__.py
adp_connection/lib/adpapiconnection.py
adp_connection/lib/adpapiconnectionfactory.py
adp_connection/lib/connectexceptions.py
adp_connection/lib/connectionconfiguration.py
tests/__init__.py
tests/base.py
tests/test_connections.py
tests/test_version.py