Metadata-Version: 1.1
Name: adp-connection
Version: 1.0
Summary: A library to help connect to ADP using Openid-Connect and OAuth 2.0
Home-page: https://github.com/adplabs/adp-connection-python
Author: Copyright © 2015-2016 ADP, LLC.
Author-email: Vishal.Shah-Contractor@adp.com
License: Apache 2.0
Keywords: client_credentials authorization_code adp connect api
Platform: UNKNOWN
Classifier: Development Status :: 4 - Beta
Classifier: Intended Audience :: Developers
Classifier: License :: OSI Approved :: Apache Software License
Classifier: Natural Language :: English
Classifier: Operating System :: Unix
Classifier: Programming Language :: Python :: 2.7
Classifier: Programming Language :: Python :: Implementation :: PyPy
Classifier: Operating System :: OS Independent
